{"fielding_in":[],"other_officers":[],"campaigns_officer":"None","registered_date":"2007-03-30T00:00:00","postcode":"BN7 1YH","party_leader":"Mr Robert Shepherd","nominating_officer":"Mr Martin Leeburn","emblems":[],"party_address":"2 Mount Place\r\nLewes\r\nEast Sussex\r\nBN7 1YH\r\nUnited Kingdom\r\n","email":"","gibraltar_party":false,"financial_year_end":"31/12","status":"Voluntarily Deregistered","fax":"","end_date":"2009-12-31T00:00:00","phone_extension":"","phone":"","treasurer":"Miss Catherine Darcy","party_id":"PP663","accounting_units":{"exempt_from_parliamentary_election_returns":false,"exempt_from_quarterly_transaction_returns":false,"exempt_from_quarterly_donation_returns":true},"geometry":{"type":"Point","coordinates":[0.009516382566130488,50.87438489164135]},"register":"Great Britain","party_name":"Friends of The Lewes Arms [De-registered 10/04/08]","alternative_names":[""],"descriptions":[]}