{"fielding_in":[],"other_officers":[],"campaigns_officer":null,"registered_date":"2004-08-31T00:00:00","postcode":"SW1H 9HP","party_leader":null,"nominating_officer":null,"emblems":[],"party_address":"16 Old Queen Street\r\nno town\r\nLondon\r\nSW1H 9HP\r\nUnited Kingdom\r\n","email":"","gibraltar_party":false,"financial_year_end":null,"status":"Authorised","fax":"","end_date":null,"phone_extension":"","phone":"","treasurer":null,"party_id":"PerPar982","accounting_units":{"exempt_from_parliamentary_election_returns":null,"exempt_from_quarterly_transaction_returns":null,"exempt_from_quarterly_donation_returns":null},"geometry":{"type":"Point","coordinates":[-0.1309114573536641,51.501001137419784]},"register":null,"party_name":"The Labour Party","alternative_names":[],"descriptions":[]}