{"fielding_in":[],"other_officers":[],"campaigns_officer":"None","registered_date":"2013-11-19T00:00:00","postcode":"MC98000","party_leader":"Mr Russell Dean","nominating_officer":"Mrs Dawn Dean","emblems":[],"party_address":"LE REGINA\r\n15 BOULEVARD DES MOULINS\r\nMONTE CARLO\r\nMC98000\r\nMonaco\r\n","email":"","gibraltar_party":false,"financial_year_end":"31/12","status":"Authorised","fax":"","end_date":null,"phone_extension":"","phone":"","treasurer":"Mr Russell Dean","party_id":"PP2168","accounting_units":{"exempt_from_parliamentary_election_returns":false,"exempt_from_quarterly_transaction_returns":false,"exempt_from_quarterly_donation_returns":false},"geometry":{"type":"Point","coordinates":[7.424615799999999,43.73841760000001]},"register":"Great Britain","party_name":"THE PARTY PARTY","alternative_names":[""],"descriptions":[]}