{"fielding_in":[],"other_officers":[],"campaigns_officer":"None","registered_date":"2010-12-07T00:00:00","postcode":"B6 4LD","party_leader":"Ms Nikki Sinclaire MEP","nominating_officer":"Ms Nicole Jayne Carroll","emblems":[{"image":"raw_data/PP882/Emblem_562.jpg","id":"562","description":"A representation of a flag and text"},{"image":"raw_data/PP882/Emblem_563.gif","id":"563","description":"I on Union Flag D with dot and text"},{"image":"raw_data/PP882/Emblem_564.gif","id":"564","description":"Text with ID highlighted"}],"party_address":"123 New John Street\r\nBirmingham\r\nWest Midlands\r\nB6 4LD\r\nUnited Kingdom\r\n","email":"","gibraltar_party":false,"financial_year_end":"31/12","status":"Authorised","fax":"","end_date":null,"phone_extension":"","phone":"","treasurer":"Ms Claire Furber","party_id":"PP882","accounting_units":{"exempt_from_parliamentary_election_returns":true,"exempt_from_quarterly_transaction_returns":true,"exempt_from_quarterly_donation_returns":false},"geometry":{"type":"Point","coordinates":[-1.8916903580409599,52.491833595091805]},"register":"Great Britain","party_name":"We Demand A Referendum Now","alternative_names":[""],"descriptions":[{"translation":"","description":"RE-ELECT NIKKI SINCLAIRE MEP"},{"translation":"","description":"Yes to UK NO to EU"},{"translation":"","description":"Vote No to European Union Membership"},{"translation":"","description":"Referendum Now"},{"translation":"","description":"Let the people decide"},{"translation":"","description":"The Campaign for a Referendum Party"},{"translation":"","description":"Less Europe More Britain"},{"translation":"","description":"Working for Less Europe More Britain"},{"translation":"","description":"Operation Christian Vote"}]}